brownie/__init__.py
brownie/_config.py
brownie/_expansion.py
brownie/_singleton.py
brownie/exceptions.py
brownie/typing.py
brownie/_cli/__init__.py
brownie/_cli/__main__.py
brownie/_cli/accounts.py
brownie/_cli/bake.py
brownie/_cli/compile.py
brownie/_cli/console.py
brownie/_cli/gui.py
brownie/_cli/init.py
brownie/_cli/networks.py
brownie/_cli/pm.py
brownie/_cli/run.py
brownie/_cli/test.py
brownie/_gui/__init__.py
brownie/_gui/bases.py
brownie/_gui/console.py
brownie/_gui/opcodes.py
brownie/_gui/report.py
brownie/_gui/root.py
brownie/_gui/source.py
brownie/_gui/styles.py
brownie/_gui/tooltip.py
brownie/convert/__init__.py
brownie/convert/datatypes.py
brownie/convert/main.py
brownie/convert/normalize.py
brownie/convert/utils.py
brownie/data/default-config.yaml
brownie/data/network-config.yaml
brownie/data/providers-config.yaml
brownie/data/contracts/Multicall2.sol
brownie/data/interfaces/ERC20.json
brownie/data/interfaces/Multicall2.json
brownie/network/__init__.py
brownie/network/account.py
brownie/network/alert.py
brownie/network/contract.py
brownie/network/event.py
brownie/network/main.py
brownie/network/multicall.py
brownie/network/state.py
brownie/network/transaction.py
brownie/network/web3.py
brownie/network/gas/__init__.py
brownie/network/gas/bases.py
brownie/network/gas/strategies.py
brownie/network/middlewares/__init__.py
brownie/network/middlewares/caching.py
brownie/network/middlewares/catch_tx_revert.py
brownie/network/middlewares/ganache7.py
brownie/network/middlewares/geth_poa.py
brownie/network/middlewares/hardhat.py
brownie/network/rpc/__init__.py
brownie/network/rpc/anvil.py
brownie/network/rpc/ganache.py
brownie/network/rpc/geth.py
brownie/network/rpc/hardhat.py
brownie/project/__init__.py
brownie/project/build.py
brownie/project/flattener.py
brownie/project/main.py
brownie/project/scripts.py
brownie/project/sources.py
brownie/project/compiler/__init__.py
brownie/project/compiler/solidity.py
brownie/project/compiler/utils.py
eth_brownie-1.20.5.dist-info/LICENSE
eth_brownie-1.20.5.dist-info/METADATA
eth_brownie-1.20.5.dist-info/WHEEL
eth_brownie-1.20.5.dist-info/entry_points.txt
eth_brownie-1.20.5.dist-info/top_level.txt
eth_brownie-1.20.5.dist-info/RECORD
