Metadata-Version: 2.1
Name: eth-brownie
Version: 1.20.5
Summary: A Python framework for Ethereum smart contract deployment, testing and interaction.
Home-page: https://github.com/eth-brownie/brownie
Author: Ben Hauser
Author-email: ben@hauser.id
License: MIT
Keywords: brownie
Classifier: Development Status :: 5 - Production/Stable
Classifier: Intended Audience :: Developers
Classifier: Topic :: Software Development :: Build Tools
Classifier: License :: OSI Approved :: MIT License
Classifier: Programming Language :: Python :: 3
Classifier: Programming Language :: Python :: 3.10
Classifier: Programming Language :: Python :: 3.11
Classifier: Programming Language :: Python :: 3.12
Requires-Python: >=3.10,<4
License-File: LICENSE
Requires-Dist: aiohttp==3.9.3
Requires-Dist: aiosignal==1.3.1
Requires-Dist: asttokens==2.4.1
Requires-Dist: attrs==23.2.0
Requires-Dist: bitarray==2.9.2
Requires-Dist: black==24.2.0
Requires-Dist: cbor2==5.6.2
Requires-Dist: certifi==2024.2.2
Requires-Dist: charset-normalizer==3.3.2
Requires-Dist: click==8.1.7
Requires-Dist: cytoolz==0.12.3
Requires-Dist: dataclassy==0.11.1
Requires-Dist: eip712==0.2.4
Requires-Dist: eth-abi==5.0.0
Requires-Dist: eth-account==0.10.0
Requires-Dist: eth-event==1.2.5
Requires-Dist: eth-hash[pycryptodome]==0.6.0
Requires-Dist: eth-keyfile==0.7.0
Requires-Dist: eth-keys==0.5.0
Requires-Dist: eth-rlp==1.0.1
Requires-Dist: eth-typing==3.5.2
Requires-Dist: eth-utils==2.3.1
Requires-Dist: execnet==2.0.2
Requires-Dist: frozenlist==1.4.1
Requires-Dist: hexbytes==0.3.1
Requires-Dist: hypothesis==6.27.3
Requires-Dist: idna==3.6
Requires-Dist: importlib-metadata==7.0.1
Requires-Dist: iniconfig==2.0.0
Requires-Dist: jsonschema==4.21.1
Requires-Dist: jsonschema-specifications==2023.12.1
Requires-Dist: lazy-object-proxy==1.10.0
Requires-Dist: lru-dict==1.2.0
Requires-Dist: multidict==6.0.5
Requires-Dist: mypy-extensions==1.0.0
Requires-Dist: packaging==23.2
Requires-Dist: parsimonious==0.9.0
Requires-Dist: pathspec==0.12.1
Requires-Dist: platformdirs==4.2.0
Requires-Dist: pluggy==1.4.0
Requires-Dist: prompt-toolkit==3.0.43
Requires-Dist: protobuf==4.25.3
Requires-Dist: psutil==5.9.8
Requires-Dist: py==1.11.0
Requires-Dist: py-solc-ast==1.2.10
Requires-Dist: py-solc-x==1.1.1
Requires-Dist: pycryptodome==3.20.0
Requires-Dist: pygments==2.17.2
Requires-Dist: pygments-lexer-solidity==0.7.0
Requires-Dist: pytest==6.2.5
Requires-Dist: pytest-forked==1.6.0
Requires-Dist: pytest-xdist==1.34.0
Requires-Dist: python-dotenv==0.16.0
Requires-Dist: pyunormalize==15.1.0
Requires-Dist: pyyaml==6.0.1
Requires-Dist: referencing==0.33.0
Requires-Dist: regex==2023.12.25
Requires-Dist: requests==2.31.0
Requires-Dist: rlp==4.0.0
Requires-Dist: rpds-py==0.18.0
Requires-Dist: semantic-version==2.10.0
Requires-Dist: six==1.16.0
Requires-Dist: sortedcontainers==2.4.0
Requires-Dist: toml==0.10.2
Requires-Dist: toolz==0.12.1
Requires-Dist: tqdm==4.66.2
Requires-Dist: typing-extensions==4.9.0
Requires-Dist: urllib3==2.2.1
Requires-Dist: vvm==0.1.0
Requires-Dist: vyper==0.3.10
Requires-Dist: wcwidth==0.2.13
Requires-Dist: web3==6.15.1
Requires-Dist: websockets==12.0
Requires-Dist: wheel==0.42.0
Requires-Dist: wrapt==1.16.0
Requires-Dist: yarl==1.9.4
Requires-Dist: zipp==3.17.0
